
{
  "campi": [
            {
            "name": "CUASO",
            "restaurants": [
                            {
                            "address": "Praça do Relógio Solar, travessa 8, nº 300,Cidade Universitária, São Paulo - SP",
                            "alias": "Central",
                            "name": "Restaurante Central",
                            "phones": [
                                       "(11) 3091-3318"
                                       ],
                            "id": 10,
                            "latitude": -23.559803,
                            "longitude": -46.721447,
                            "photourl": "http://www.usp.br/coseas/COSEASHP/ALM/fotosnovaRestCentral/SAS-USP%20Restaurante%20Central%20252-12%20Foto%20Francisco%20Emolo%20043.jpg",
                            "workinghours": {
                            "sunday": {
                            "lunch": "12h00 às 14h15",
                            "breakfast": "8h00 às 9h30"
                            },
                            "weekdays": {
                            "dinner": "17h30 às 19h45",
                            "lunch": "11h15 às 14h15",
                            "breakfast": "7h00 às 8h30"
                            },
                            "saturday": {
                            "lunch": "11h15 às 14h15",
                            "breakfast": "7h30 às 9h00"
                            }
                            }
                            },
                            {
                            "address": "Rua do Matão, Travessa R 187 - Instituto de Física - Universitária, São Paulo - SP ",
                            "alias": "Física",
                            "name": "Restaurante da Fisica",
                            "phones": [
                                       "(11) 3091-6710"
                                       ],
                            "id": 20,
                            "latitude": -23560594,
                            "longitude": -46735311,
                            "photourl": "http://www.usp.br/coseas/COSEASHP/ALM/FotosRestFisica/FisicaNova5Mini.jpg",
                            "workinghours": {
                            "weekdays": {
                            "dinner": "17h30 às 19h45",
                            "lunch": "11h15 às 14h15",
                            "breakfast": "7h00 às 8h30"
                            }
                            },
                            "rucard": {
                            "address": "Tesouraria da Faculdade Saúde Pública",
                            "workinghours": "Terças a Sextas-feiras das 09h00 às 13h45min e 14:30 às 16h00"
                            },
                            "cashier": {
                            "address": "Tesouraria da Faculdade Saúde Pública",
                            "longitude": 0,
                            "latitude": 0,
                            "workinghours": "Segundas-feiras das 10h00 às 13h45min e das 15h00 às 19h00\nTerças a Sextas-feiras das 09h00 às 13h45min e 14:30 às 16h00",
                            "prices": {
                            "special": {
                            "dinner": "6,00",
                            "lunch": "6,00",
                            "breakfast": "6,00"
                            },
                            "students": {
                            "dinner": "1,90",
                            "lunch": "1,90",
                            "breakfast": "1,90"
                            },
                            "visiting": {
                            "dinner": "12,00",
                            "lunch": "12,00",
                            "breakfast": "12,00"
                            }
                            }
                            }
                            
                            }
                            ]
            },
            {
            "name": "Direito",
            "restaurants": [
                            {
                            "address": "Rua Riachuelo, 194 - Faculdade de Direito - Largo São Francisco, São Paulo - SP ",
                            "alias": "Direito",
                            "name": "Restaurante da Faculdade de Direito",
                            "phones": [
                                       "(11) 3111-4054"
                                       ],
                            "id": 80,
                            "latitude": 0,
                            "longitude": 0,
                            "photourl": "http://www.usp.br/coseas/COSEASHP/ALM/Rest%20Fac%20Direito/Dir1.jpg",
                            "workinghours": {
                            "weekdays": {
                            "dinner": "17h30 às 19h00",
                            "lunch": "11h30 às 14h00"
                            }
                            },
                            "rucard": {
                            "address": "Tesouraria da Faculdade Saúde Pública",
                            "workinghours": "Terças a Sextas-feiras das 09h00 às 13h45min e 14:30 às 16h00"
                            },
                            "cashier": {
                            "address": "Tesouraria da Faculdade Saúde Pública",
                            "longitude": 0,
                            "latitude": 0,
                            "workinghours": "Segundas-feiras das 10h00 às 13h45min e das 15h00 às 19h00\nTerças a Sextas-feiras das 09h00 às 13h45min e 14:30 às 16h00",
                            "prices": {
                            "special": {
                            "dinner": "6,00",
                            "lunch": "6,00",
                            "breakfast": "6,00"
                            },
                            "students": {
                            "dinner": "1,90",
                            "lunch": "1,90",
                            "breakfast": "1,90"
                            },
                            "visiting": {
                            "dinner": "12,00",
                            "lunch": "12,00",
                            "breakfast": "12,00"
                            }
                            }
                            }
                            
                            }
                            ]
            },
            {
            "name": "EEL",
            "restaurants": [
                            {
                            "address": "Estrada do Campinho - Lorena – São Paulo",
                            "alias": "EEL",
                            "name": "Restaurante da EEL - Lorena",
                            "phones": [
                                       "(12) 3159-5304"
                                       ],
                            "id": 70,
                            "latitude": 0,
                            "longitude": 0,
                            "photourl": "http://www.usp.br/coseas/COSEASHP/ALM/EEL/Lorena_0278.JPG",
                            "workinghours": {
                            "weekdays": {
                            "dinner": "17h30 às 19h30",
                            "lunch": "11h00 às 14h00"
                            }
                            },
                            "rucard": {
                            "address": "Tesouraria da Faculdade Saúde Pública",
                            "workinghours": "Terças a Sextas-feiras das 09h00 às 13h45min e 14:30 às 16h00"
                            },
                            "cashier": {
                            "address": "Tesouraria da Faculdade Saúde Pública",
                            "longitude": 0,
                            "latitude": 0,
                            "workinghours": "Segundas-feiras das 10h00 às 13h45min e das 15h00 às 19h00\nTerças a Sextas-feiras das 09h00 às 13h45min e 14:30 às 16h00",
                            "prices": {
                            "special": {
                            "dinner": "6,00",
                            "lunch": "6,00",
                            "breakfast": "6,00"
                            },
                            "students": {
                            "dinner": "1,90",
                            "lunch": "1,90",
                            "breakfast": "1,90"
                            },
                            "visiting": {
                            "dinner": "12,00",
                            "lunch": "12,00",
                            "breakfast": "12,00"
                            }
                            }
                            }
                            
                            }
                            ]
            },
            {
            "name": "FSP",
            "restaurants": [{
                            "address": "Av. Dr. Arnaldo, 715 - Faculdade de Saúde Pública, Cerqueira Cesar, São Paulo - SP",
                            "alias": "FSP",
                            "name": "Restaurante da Faculdade de Saúde Pública",
                            "phones": [
                                       "(11) 3061-7785"
                                       ],
                            "id": 90,
                            "latitude": 0,
                            "longitude": 0,
                            "photourl": "http://www.usp.br/coseas/COSEASHP/ALM/RestFSP/FSP3Mini.jpg",
                            "workinghours": {
                            "weekdays": {
                            "dinner": "17h30 às 19h00",
                            "lunch": "11h15 às 14h15"
                            }
                            },
                            "rucard": {
                            "address": "Tesouraria da Faculdade Saúde Pública",
                            "workinghours": "Terças a Sextas-feiras das 09h00 às 13h45min e 14:30 às 16h00"
                            },
                            "cashier": {
                            "address": "Tesouraria da Faculdade Saúde Pública",
                            "longitude": 0,
                            "latitude": 0,
                            "workinghours": "Segundas-feiras das 10h00 às 13h45min e das 15h00 às 19h00\nTerças a Sextas-feiras das 09h00 às 13h45min e 14:30 às 16h00",
                            "prices": {
                            "special": {
                            "dinner": "6,00",
                            "lunch": "6,00",
                            "breakfast": "6,00"
                            },
                            "students": {
                            "dinner": "1,90",
                            "lunch": "1,90",
                            "breakfast": "1,90"
                            },
                            "visiting": {
                            "dinner": "12,00",
                            "lunch": "12,00",
                            "breakfast": "12,00"
                            }
                            }
                            }
                            }]
            }
            ]
}
